setup.py
asposetaskscloud/ApiClient.py
asposetaskscloud/TasksApi.py
asposetaskscloud/__init__.py
asposetaskscloud.egg-info/PKG-INFO
asposetaskscloud.egg-info/SOURCES.txt
asposetaskscloud.egg-info/dependency_links.txt
asposetaskscloud.egg-info/requires.txt
asposetaskscloud.egg-info/top_level.txt
asposetaskscloud/models/AssignmentItem.py
asposetaskscloud/models/AssignmentItemResponse.py
asposetaskscloud/models/AssignmentItems.py
asposetaskscloud/models/AssignmentItemsResponse.py
asposetaskscloud/models/AssignmentResponse.py
asposetaskscloud/models/AssignmentsResponse.py
asposetaskscloud/models/BookingType.py
asposetaskscloud/models/CalculationType.py
asposetaskscloud/models/Calendar.py
asposetaskscloud/models/CalendarException.py
asposetaskscloud/models/CalendarExceptionType.py
asposetaskscloud/models/CalendarExceptionsResponse.py
asposetaskscloud/models/CalendarItem.py
asposetaskscloud/models/CalendarItemResponse.py
asposetaskscloud/models/CalendarItems.py
asposetaskscloud/models/CalendarItemsResponse.py
asposetaskscloud/models/CalendarResponse.py
asposetaskscloud/models/ConstraintType.py
asposetaskscloud/models/CostAccrualType.py
asposetaskscloud/models/CustomFieldType.py
asposetaskscloud/models/DateTime.py
asposetaskscloud/models/DayType.py
asposetaskscloud/models/Document.py
asposetaskscloud/models/DocumentProperties.py
asposetaskscloud/models/DocumentPropertiesResponse.py
asposetaskscloud/models/DocumentProperty.py
asposetaskscloud/models/DocumentPropertyResponse.py
asposetaskscloud/models/DocumentResponse.py
asposetaskscloud/models/ElementType.py
asposetaskscloud/models/ExtendedAttribute.py
asposetaskscloud/models/ExtendedAttributeDefinition.py
asposetaskscloud/models/ExtendedAttributeItem.py
asposetaskscloud/models/ExtendedAttributeItems.py
asposetaskscloud/models/ExtendedAttributeItemsResponse.py
asposetaskscloud/models/ExtendedAttributeResponse.py
asposetaskscloud/models/Link.py
asposetaskscloud/models/MaskType.py
asposetaskscloud/models/Month.py
asposetaskscloud/models/MonthItemType.py
asposetaskscloud/models/MonthPosition.py
asposetaskscloud/models/OrdinalNumber.py
asposetaskscloud/models/OutlineCode.py
asposetaskscloud/models/OutlineCodeDefinition.py
