Metadata-Version: 1.1
Name: asposetaskscloud
Version: 1.0.0
Summary: Aspose.Tasks Cloud SDK for Python allows you to use Aspose.Tasks APIs in your Python applications
Home-page: http://www.aspose.com/cloud/project-management-api.aspx
Author: Farooq Sheikh
Author-email: farooq.sheikh@aspose.com
License: UNKNOWN
Platform: UNKNOWN
Classifier: Programming Language :: Python
Classifier: Programming Language :: Python :: 2
Classifier: License :: OSI Approved :: MIT License
Classifier: Operating System :: OS Independent
